xt_models/models/__init__.py
xt_models/models/pspnet.py
xt_models/models/resnet.py
xt_models/models/ses.py
xt_models/models/object_detection/__init__.py
xt_models/models/object_detection/models.py
xt_models/models/object_detection/utils.py
xt_models/models/semantic_segmentation/__init__.py
xt_models/models/semantic_segmentation/hrnet.py
xt_models/models/semantic_segmentation/mobilenet.py
xt_models/models/semantic_segmentation/models.py
xt_models/models/semantic_segmentation/resnet.py
xt_models/models/semantic_segmentation/resnext.py
xt_models/models/semantic_segmentation/utils.py
xt_models/utils/__init__.py
xt_models-0.4.1.dist-info/METADATA
xt_models-0.4.1.dist-info/WHEEL
xt_models-0.4.1.dist-info/top_level.txt
xt_models-0.4.1.dist-info/RECORD
