Metadata-Version: 2.1
Name: xt-models
Version: 0.4.1
Summary: Models and model utilities for common ML tasks
Home-page: https://github.com/XtractTech/xt-models
Author: Xtract AI
Author-email: info@xtract.ai
License: UNKNOWN
Platform: UNKNOWN
Classifier: Programming Language :: Python :: 3
Classifier: Operating System :: OS Independent
Provides: xt_models
Requires-Dist: numpy
Requires-Dist: torch
Requires-Dist: torchvision
Requires-Dist: transformers
